{
    "crs": {
        "properties": {
            "name": "urn:ogc:def:crs:EPSG::3857"
        },
        "type": "name"
    },
    "features": [
        {
            "geometry": {
                "coordinates": [
                    0.6480720043182373,
                    -0.5750709772109985
                ],
                "type": "Point"
            },
            "properties": {
                "frame": "map",
                "id": 0
            },
            "type": "Feature"
        },
        {
            "geometry": {
                "coordinates": [
                    0.6134880185127258,
                    0.390608012676239
                ],
                "type": "Point"
            },
            "properties": {
                "frame": "map",
                "id": 1
            },
            "type": "Feature"
        },
        {
            "geometry": {
                "coordinates": [
                    2.2912280559539795,
                    0.37817299365997314
                ],
                "type": "Point"
            },
            "properties": {
                "frame": "map",
                "id": 2
            },
            "type": "Feature"
        },
        {
            "geometry": {
                "coordinates": [
                    2.3645589351654053,
                    -0.6586369872093201
                ],
                "type": "Point"
            },
            "properties": {
                "frame": "map",
                "id": 3
            },
            "type": "Feature"
        },
        {
            "geometry": {
                "type": "MultiLineString"
            },
            "properties": {
                "cost": 0.0,
                "endid": 1,
                "id": 4,
                "overridable": true,
                "startid": 0
            },
            "type": "Feature"
        },
        {
            "geometry": {
                "type": "MultiLineString"
            },
            "properties": {
                "cost": 0.0,
                "endid": 0,
                "id": 5,
                "overridable": true,
                "startid": 1
            },
            "type": "Feature"
        },
        {
            "geometry": {
                "type": "MultiLineString"
            },
            "properties": {
                "cost": 0.0,
                "endid": 2,
                "id": 6,
                "overridable": true,
                "startid": 1
            },
            "type": "Feature"
        },
        {
            "geometry": {
                "type": "MultiLineString"
            },
            "properties": {
                "cost": 0.0,
                "endid": 1,
                "id": 7,
                "overridable": true,
                "startid": 2
            },
            "type": "Feature"
        },
        {
            "geometry": {
                "type": "MultiLineString"
            },
            "properties": {
                "cost": 0.0,
                "endid": 3,
                "id": 8,
                "overridable": true,
                "startid": 2
            },
            "type": "Feature"
        },
        {
            "geometry": {
                "type": "MultiLineString"
            },
            "properties": {
                "cost": 0.0,
                "endid": 2,
                "id": 9,
                "overridable": true,
                "startid": 3
            },
            "type": "Feature"
        }
    ],
    "name": "graph",
    "type": "FeatureCollection"
}
